README.rst
filehandle.py
setup.py
filehandle.egg-info/PKG-INFO
filehandle.egg-info/SOURCES.txt
filehandle.egg-info/dependency_links.txt
filehandle.egg-info/top_level.txt