Metadata-Version: 1.0
Name: filehandle
Version: 0.0.9
Summary: Normalize the way you get a file handle from either gzip or normal file
Home-page: https://github.com/necrolyte2/filehandle
Author: Tyghe Vallard
Author-email: vallardt@gmail.com
License: GPL v2
Keywords: gzip,handle,open,file
Platform: UNKNOWN
